<?xml version="1.0" encoding="utf-8" ?>
<map version="1.0" orientation="orthogonal" width="50" height="100" tilewidth="128" tileheight="128">
	<properties>
		<property name="aim0" value="2" />
		<property name="aim1" value="1" />
		<property name="aim2" value="12" />
		<property name="consistentToughness" value="true" />
		<property name="donationItem" value="131" />
		<property name="donationQuantity" value="1" />
		<property name="introConv" value="SS>We're nearly there, only *Hone*W ingredient to go!\nSS>Unfortunately the zombies seem to be one step ahead of us, they've hidden all the *Hpumpkins*W they can find.\nSM&lt;Have they hidden them underground by any chance?\nSS>How did you know?!\nSS>We need *Hfive pumpkins*W, get to it!" />
		<property name="museum" value="true" />
		<property name="npcConv0" value="ST>Nothing interesting down this old mine, no need to investigate further. *RThe Zombies*W." />
		<property name="npcConv1" value="SA>*RZombies!*W They were everywhere! Carrying *Hpumpkins*W they were.\nSA>I hid up here and it's all gone quiet, I think they *Rcollapsed*W the whole cave network." />
		<property name="npcConv2" value="SA>Th..th..thankyou for s..saving me!\nSA>I h..hid down h..here from the z..zo..zombies, and got fr..fr..frozen!" />
		<property name="npcConv3" value="SS>This poor man is frozen solid! If you can find some salt we can *Hdefrost him*w*2" />
		<property name="objective2" value="Defrost 1 miner" />
		<property name="objectivehidden2" value="true" />
		<property name="outroConv" value="SS>That's all the ingredients we need, let's hurry up and make this potion!" />
		<property name="shop" value="true" />
		<property name="startX" value="0" />
		<property name="startY" value="0" />
		<property name="stopOnPrimaryComplete" value="false" />
		<property name="targetNum0" value="5" />
		<property name="targetNum1" value="150" />
		<property name="targetNum2" value="1" />
		<property name="targetType0" value="221" />
		<property name="targetType1" value="-1" />
		<property name="targetType2" value="-1" />
		<property name="theme" value="2" />
	</properties>
	<tileset firstgid="1" name="tileset" tilewidth="128" tileheight="128">
		<image source="tileset.png" width="1280" height="1536" />
	</tileset>
	<layer name="main" width="50" height="100">
		<data encoding="csv">"
2,2,2,2,2,2,2,2,2,2,2,2,2,2,2,2,2,2,2,2,2,2,2,2,2,2,2,2,2,2,2,2,2,2,2,2,2,2,2,2,2,2,2,2,2,2,2,2,2,2,
2,2,2,2,2,2,2,2,2,2,2,2,2,2,2,2,2,2,2,2,2,2,2,2,2,2,2,2,2,2,2,2,2,2,2,2,2,2,2,2,2,2,2,2,2,2,2,2,2,2,
2,2,2,2,2,2,2,2,2,2,2,2,2,2,2,2,2,2,2,2,2,2,2,2,2,2,2,2,2,2,2,2,2,2,2,2,2,2,2,2,2,2,2,2,2,2,2,2,2,2,
2,2,2,2,2,2,2,2,2,2,2,2,2,2,2,2,2,2,2,2,2,2,2,2,2,2,2,2,2,2,2,2,2,2,2,2,2,2,2,2,2,2,2,2,2,2,2,2,2,2,
2,2,2,2,2,2,2,2,2,2,2,2,2,2,2,2,2,2,2,2,2,2,2,2,2,2,2,2,2,2,2,2,2,2,2,2,2,2,2,2,2,2,2,2,2,2,2,2,2,2,
1,1,3,3,3,3,3,3,3,3,3,3,3,3,3,3,3,3,3,3,3,3,3,3,3,1,1,3,3,9,1,3,3,3,3,3,3,3,3,3,3,3,3,3,3,3,3,3,3,1,
1,1,1,3,3,3,3,3,3,3,3,3,3,3,3,3,3,3,3,3,3,3,3,3,3,3,1,1,3,9,1,3,1,3,3,3,3,3,3,3,3,3,3,3,3,3,3,3,1,1,
1,1,3,3,3,3,3,8,8,8,3,3,3,3,3,3,3,3,3,8,3,3,3,3,3,3,3,1,3,9,3,1,1,3,3,3,3,3,8,3,3,3,3,3,3,3,3,3,3,1,
1,1,1,3,3,3,3,3,3,3,3,3,3,3,3,3,3,3,9,9,9,9,3,3,3,3,8,3,9,9,3,3,3,3,3,3,3,3,3,8,3,3,3,3,3,3,3,3,1,1,
1,1,3,3,3,3,3,3,3,3,3,3,3,8,3,3,3,3,3,3,9,3,3,3,3,3,3,1,3,9,3,1,3,9,3,3,3,3,3,3,3,3,3,3,3,3,3,3,1,1,
1,1,1,3,3,3,3,3,3,3,3,3,3,3,3,3,3,3,3,3,9,9,9,3,3,3,1,1,3,9,3,3,9,9,9,3,3,3,3,3,3,3,3,3,3,3,3,3,3,1,
1,1,3,3,3,3,3,3,3,3,3,3,3,3,3,3,3,3,3,3,3,3,3,3,3,3,3,3,9,9,9,1,9,3,3,3,3,3,3,3,8,3,3,3,3,3,3,3,1,1,
1,1,1,3,3,3,3,3,3,3,8,3,3,3,3,3,3,3,3,3,3,3,3,3,3,3,9,9,9,9,9,9,9,3,3,3,3,3,3,8,3,3,3,3,3,8,3,3,3,1,
1,1,1,3,3,3,3,3,3,3,3,3,3,3,3,8,3,3,3,3,3,3,3,3,8,3,3,3,3,3,3,3,3,3,3,3,3,3,9,9,9,3,3,3,3,8,3,3,3,1,
1,1,1,3,3,3,3,3,3,3,3,3,3,3,3,3,3,3,3,3,3,3,3,3,3,3,3,3,3,3,3,3,3,8,3,3,3,3,9,3,3,3,3,3,3,3,3,3,1,1,
1,1,3,3,3,3,8,3,3,3,3,3,3,3,3,3,3,3,3,3,3,3,3,3,3,3,3,3,3,3,3,3,3,3,3,3,9,9,9,9,3,3,3,3,3,3,3,3,3,1,
1,1,3,3,3,3,3,3,3,3,3,3,3,3,3,3,3,3,3,3,3,3,3,3,3,3,3,3,3,3,3,8,8,3,3,3,3,3,3,9,9,3,3,3,3,3,3,3,3,1,
1,1,3,3,3,3,3,3,3,3,3,3,3,3,3,9,3,3,3,3,3,3,8,3,3,3,3,3,3,3,3,3,8,3,3,3,3,3,3,3,3,3,3,3,3,3,3,3,1,1,
1,1,1,3,3,3,3,3,3,3,3,3,3,3,9,9,9,9,3,8,3,3,3,3,3,3,3,3,3,3,3,3,3,3,3,3,3,3,3,3,3,3,3,3,3,3,3,3,3,1,
1,1,1,3,3,3,3,8,3,3,3,3,3,9,9,9,9,9,9,9,9,9,3,3,3,3,3,3,3,3,3,3,3,3,3,3,3,3,3,3,3,3,3,3,3,8,3,3,1,1,
1,1,3,3,3,3,3,3,3,3,3,3,3,3,3,3,9,3,3,3,3,3,3,3,3,8,3,3,3,3,3,3,3,3,3,3,3,3,3,3,3,3,3,3,3,3,3,3,1,1,
1,1,3,3,3,3,3,3,3,3,3,3,3,3,3,3,9,3,3,3,3,3,3,3,3,3,3,3,3,8,3,3,3,3,3,3,3,3,3,3,3,3,3,3,3,3,3,3,3,1,
1,1,3,3,3,3,3,3,3,3,3,3,3,3,9,9,9,3,3,3,3,3,3,3,3,3,3,3,3,3,3,3,3,3,3,3,3,3,3,3,3,3,3,3,3,3,3,3,3,1,
1,1,1,3,3,3,3,3,3,3,3,3,3,3,3,3,9,3,3,3,3,3,8,8,3,3,3,3,3,3,3,3,3,3,3,3,3,3,3,3,3,3,3,3,3,3,3,3,3,1,
1,1,1,3,3,3,3,8,3,3,3,3,3,3,3,3,3,3,3,3,3,3,8,3,3,3,3,3,3,3,3,3,3,3,3,3,3,3,3,3,3,3,3,8,8,3,3,3,1,1,
1,1,1,3,3,3,3,3,3,3,3,3,3,3,3,3,3,3,3,3,3,3,3,3,3,3,3,3,3,3,8,3,3,3,3,8,3,3,3,3,3,3,3,3,3,3,3,3,3,1,
1,1,1,3,3,3,3,3,3,3,3,3,3,3,3,3,3,3,3,3,3,3,3,3,3,3,3,3,3,3,3,3,3,3,3,3,3,3,3,3,8,3,3,3,3,3,3,3,1,1,
1,1,3,3,3,3,3,9,3,3,3,3,3,3,3,3,3,3,3,3,3,3,3,3,9,9,9,9,9,3,3,3,8,3,3,3,3,3,3,3,3,3,3,3,3,3,3,3,1,1,
1,1,3,3,3,9,9,9,9,9,3,3,3,8,8,3,3,3,3,3,3,3,3,3,3,8,3,9,3,3,3,3,3,3,3,3,9,3,3,3,3,3,3,3,3,3,3,3,3,1,
1,1,3,3,3,3,3,3,3,9,3,3,3,3,3,3,3,3,3,3,3,3,3,3,3,3,3,3,3,3,3,3,3,3,3,3,9,3,9,3,3,8,8,8,3,3,3,3,1,1,
1,1,1,3,3,3,3,3,3,3,3,3,3,3,3,3,3,3,3,3,8,3,3,3,3,3,8,8,8,3,3,3,3,3,9,9,9,9,9,3,8,3,3,3,3,3,3,3,1,1,
1,1,3,3,3,3,3,8,3,3,3,3,3,3,3,3,3,3,3,3,3,3,3,3,3,3,3,3,3,3,3,3,3,3,3,3,9,3,3,3,3,3,3,3,3,3,3,3,1,1,
1,1,3,3,3,3,3,3,3,3,3,3,3,3,3,3,3,3,8,3,3,3,3,3,3,3,3,3,3,3,3,3,3,3,9,9,9,3,3,3,3,3,3,3,3,3,3,3,1,1,
1,1,1,3,3,3,3,3,3,3,3,3,3,3,3,3,3,3,3,3,3,3,3,3,3,3,3,3,8,3,3,3,3,3,3,3,3,3,3,3,3,3,3,3,3,3,3,3,3,1,
1,1,3,3,3,3,3,3,3,3,3,3,3,3,8,3,3,3,3,3,3,3,3,3,3,3,3,3,3,3,3,3,3,3,3,3,3,3,3,3,3,3,3,3,3,3,3,3,3,1,
1,1,1,3,3,3,3,8,8,3,3,3,3,3,8,3,3,3,3,3,3,3,3,3,3,3,3,3,3,3,3,3,3,3,3,3,3,8,8,3,3,3,3,3,3,3,3,3,3,1,
1,1,3,3,3,3,3,3,3,3,3,3,3,3,3,3,3,3,9,9,3,3,3,3,3,3,3,3,3,3,3,3,8,3,3,3,3,3,3,3,3,3,3,3,3,3,3,3,3,1,
1,1,1,3,3,3,3,3,3,3,3,3,3,3,3,3,3,3,3,9,9,3,3,3,3,8,3,3,3,3,3,3,3,3,3,3,3,3,3,3,3,3,3,3,8,3,3,3,3,1,
1,1,1,3,3,3,3,3,3,3,3,3,3,3,3,3,3,3,3,3,3,3,3,3,3,3,3,3,3,3,3,3,3,3,3,3,3,3,3,9,3,3,3,3,3,3,3,3,3,1,
1,1,3,3,3,3,3,3,3,3,3,3,3,3,3,3,3,3,3,3,3,3,3,3,3,3,3,3,3,3,3,3,3,3,3,3,3,3,9,9,9,9,3,3,9,3,3,3,3,1,
1,1,1,3,3,3,3,8,3,3,3,3,3,3,8,3,3,8,3,3,3,3,3,3,3,3,3,3,3,3,3,3,3,3,3,3,3,8,8,3,3,9,9,9,9,9,9,3,3,1,
1,1,3,3,3,3,3,3,3,3,3,3,3,3,3,3,3,9,3,3,3,3,3,8,3,3,3,3,3,3,8,3,3,3,3,3,3,3,3,3,3,3,9,3,3,3,3,3,3,1,
1,1,3,3,3,3,3,3,3,3,3,3,3,3,3,3,9,9,9,9,3,3,3,3,3,3,3,3,3,3,3,3,3,3,3,3,3,3,3,3,3,3,9,3,3,3,3,3,3,1,
1,1,1,3,3,3,3,3,3,3,3,3,3,3,8,3,9,3,3,3,3,3,3,3,3,3,3,3,3,3,3,3,3,3,3,3,3,3,3,3,3,9,9,3,3,8,3,3,3,1,
1,1,3,3,3,3,3,3,3,3,3,3,9,9,9,9,9,3,3,3,3,3,3,3,1,3,3,3,3,3,3,3,3,3,3,3,3,3,3,3,3,3,3,3,3,3,3,3,3,1,
1,1,3,3,3,8,3,3,3,3,3,3,3,3,3,3,3,3,3,3,3,3,3,8,1,1,1,3,3,3,3,3,3,3,3,3,3,3,3,3,3,3,3,3,3,3,3,3,1,1,
1,1,3,3,3,3,3,3,3,3,8,3,3,3,3,3,3,3,3,3,3,1,1,8,3,3,1,3,3,10,3,3,3,3,3,3,8,3,3,3,3,3,3,3,3,3,3,3,3,1,
1,1,1,3,3,3,3,3,3,3,3,3,1,3,3,3,3,3,3,3,1,1,3,3,3,3,9,3,3,3,3,10,3,3,3,3,3,3,3,3,3,3,3,3,3,3,3,3,3,1,
1,1,1,1,1,3,3,3,3,3,3,3,3,3,3,3,3,3,3,3,1,1,3,3,3,3,9,9,9,9,9,3,1,1,3,3,3,1,3,3,3,3,3,3,3,3,3,3,3,1,
1,1,1,3,3,1,1,1,1,1,1,3,3,3,1,1,1,3,3,1,1,1,1,3,3,10,10,3,9,3,9,1,3,1,1,1,1,1,1,1,3,3,3,3,3,1,1,1,1,1,
1,1,3,3,3,3,1,1,3,3,1,1,1,1,1,3,1,1,1,3,3,3,1,1,1,3,10,3,10,3,1,1,3,3,3,1,3,3,3,1,1,1,1,1,1,3,1,1,3,1,
1,1,3,3,1,1,3,1,1,3,3,3,1,1,3,1,1,3,3,1,1,1,1,1,1,1,1,10,3,3,3,3,1,3,3,1,3,3,3,3,1,1,3,3,3,3,1,3,3,1,
1,1,3,1,1,3,1,1,1,1,3,1,1,1,3,3,3,1,1,1,1,1,1,1,1,1,1,1,3,3,3,3,3,1,1,1,3,3,3,3,1,1,3,1,1,1,3,1,1,1,
1,1,1,3,3,3,3,3,3,1,1,1,1,1,1,1,1,1,1,3,1,1,1,3,3,3,1,1,1,1,1,1,3,3,1,3,1,1,1,1,1,1,1,1,3,3,1,1,1,1,
1,1,1,3,3,3,3,3,3,3,3,3,3,3,3,3,3,3,1,1,1,3,3,3,3,3,3,3,3,3,3,1,1,1,1,3,3,3,1,1,3,1,1,3,3,3,3,3,1,1,
1,1,3,3,3,3,3,3,3,3,3,3,3,3,3,3,3,3,3,3,3,3,3,3,3,3,3,3,3,3,3,3,3,3,3,3,3,3,3,3,3,3,3,3,3,3,3,3,1,1,
1,1,3,3,3,3,3,3,3,3,3,3,3,3,3,3,3,3,3,3,3,3,3,3,3,3,3,3,3,3,3,3,3,3,3,3,3,3,3,3,3,3,3,3,3,3,3,3,3,1,
1,1,3,3,3,3,3,3,3,3,3,3,3,3,3,3,3,3,3,3,3,3,3,3,3,3,3,3,3,3,3,3,3,3,3,3,3,3,3,3,3,3,3,3,3,3,3,3,3,1,
1,1,1,3,3,3,3,3,3,3,3,3,3,3,3,3,3,3,3,3,3,3,3,3,3,3,3,3,3,3,3,3,3,3,3,3,3,3,3,3,3,3,3,3,3,3,3,3,3,1,
1,1,1,3,3,3,3,3,3,3,3,3,3,3,3,3,3,3,3,3,3,3,3,3,3,3,3,3,3,3,3,3,3,3,3,3,3,3,3,3,3,3,3,3,3,3,3,3,1,1,
1,1,1,3,3,3,3,3,3,3,3,3,3,3,3,3,3,3,3,3,3,3,3,3,3,3,3,3,3,3,3,3,3,3,3,3,3,3,3,3,3,3,3,3,3,3,3,3,3,1,
1,1,1,3,3,3,3,3,3,3,3,3,3,3,3,3,3,3,3,3,3,3,3,3,3,3,3,3,3,3,3,3,3,3,3,3,3,3,3,3,3,3,3,3,3,3,3,3,1,1,
1,1,3,3,3,3,3,3,3,3,3,3,3,3,3,3,3,3,3,3,3,3,3,3,3,3,3,3,3,3,3,3,3,3,3,3,3,3,3,3,3,3,3,3,3,3,3,3,1,1,
1,1,1,3,3,3,3,3,3,3,3,3,3,3,3,3,3,3,3,3,3,3,3,3,3,3,3,3,3,3,3,3,3,3,3,3,3,3,3,3,3,3,3,3,3,3,3,3,3,1,
1,1,1,3,3,3,3,3,3,3,3,3,3,3,3,3,3,3,3,3,3,3,3,3,3,3,3,3,3,3,3,3,3,3,3,3,3,3,3,3,3,3,3,3,3,3,3,3,1,1,
1,1,3,3,3,3,3,3,3,3,3,3,3,3,3,3,3,3,3,3,3,3,3,3,3,3,3,3,3,3,3,3,3,3,3,3,3,3,3,3,3,3,3,3,3,3,3,3,3,1,
1,1,3,3,3,3,3,3,3,3,3,3,3,3,3,3,3,3,3,3,3,3,3,3,3,3,3,3,3,3,3,3,3,3,3,3,3,3,3,3,3,3,3,3,3,3,3,3,3,1,
1,1,3,3,3,3,3,3,3,3,3,3,3,3,3,3,3,3,3,3,3,3,3,3,3,3,3,3,3,3,3,3,3,3,3,3,3,3,3,3,3,3,3,3,3,3,3,3,1,1,
1,1,1,3,3,3,3,3,3,3,3,3,3,3,3,3,3,3,3,3,3,3,3,3,3,3,3,3,3,3,3,3,3,3,3,3,3,3,3,3,3,3,3,3,3,3,3,3,3,1,
1,1,1,3,3,3,3,3,3,3,3,3,3,3,3,3,3,3,3,3,3,3,3,3,3,3,3,3,3,3,3,3,3,3,3,3,3,3,3,3,3,3,3,3,3,3,3,3,1,1,
1,1,3,3,3,3,3,3,3,3,3,3,3,3,3,3,3,3,3,3,3,3,3,3,3,3,3,3,3,3,3,3,3,3,3,3,3,3,3,3,3,3,3,3,3,3,3,3,1,1,
1,1,3,3,3,3,3,3,3,3,3,3,3,3,3,3,3,3,3,3,3,3,3,3,3,3,3,3,3,3,3,3,3,3,3,3,3,3,3,3,3,3,3,3,3,3,3,3,3,1,
1,1,3,3,3,3,3,3,3,3,3,3,3,3,3,3,3,3,3,3,3,3,3,3,3,3,3,3,3,3,3,3,3,3,3,3,3,3,3,3,3,3,3,3,3,3,3,3,3,1,
1,1,1,3,3,3,3,3,3,3,3,3,3,3,3,3,3,3,3,3,3,3,3,3,3,3,3,3,3,3,3,3,3,3,3,3,3,3,3,3,3,3,3,3,3,3,3,3,3,1,
1,1,1,3,3,3,3,3,3,3,3,3,3,3,3,3,3,3,3,3,3,3,3,3,3,3,3,3,3,3,3,3,3,3,3,3,3,3,3,3,3,3,3,3,3,3,3,3,1,1,
1,1,1,3,3,3,3,3,3,3,3,3,3,3,3,3,3,3,3,3,3,3,3,3,3,3,3,3,3,3,3,3,3,3,3,3,3,3,3,3,3,3,3,3,3,3,3,3,3,1,
1,1,1,3,3,3,3,3,3,3,3,3,3,3,3,3,3,3,3,3,3,3,3,3,3,3,3,3,3,3,3,3,3,3,3,3,3,3,3,3,3,3,3,3,3,3,3,3,1,1,
1,1,3,3,3,3,3,3,3,3,3,3,3,3,3,3,3,3,3,3,3,3,3,3,3,3,3,3,3,3,3,3,3,3,3,3,3,3,3,3,3,3,3,3,3,3,3,3,1,1,
1,1,3,3,3,3,3,3,3,3,3,3,3,3,3,3,3,3,3,3,3,3,3,3,3,3,3,3,3,3,3,3,3,3,3,3,3,3,3,3,3,3,3,3,3,3,3,3,3,1,
1,1,3,3,3,3,3,3,3,3,3,3,3,3,3,3,3,3,3,3,3,3,3,3,3,3,3,3,3,3,3,3,3,3,3,3,3,3,3,3,3,3,3,3,3,3,3,3,1,1,
1,1,1,3,3,3,3,3,3,3,3,3,3,3,3,3,3,3,3,3,3,3,3,3,3,3,3,3,3,3,3,3,3,3,3,3,3,3,3,3,3,3,3,3,3,3,3,3,1,1,
1,1,3,3,3,3,3,3,3,3,3,3,3,3,3,3,3,3,3,3,3,3,3,3,3,3,3,3,3,3,3,3,3,3,3,3,3,3,3,3,3,3,3,3,3,3,3,3,1,1,
1,1,3,3,3,3,3,3,3,3,3,3,3,3,3,3,3,3,3,3,3,3,3,3,3,3,3,3,3,3,3,3,3,3,3,3,3,3,3,3,3,3,3,3,3,3,3,3,1,1,
1,1,1,3,3,3,3,3,3,3,3,3,3,3,3,3,3,3,3,3,3,3,3,3,3,3,3,3,3,3,3,3,3,3,3,3,3,3,3,3,3,3,3,3,3,3,3,3,3,1,
1,1,3,3,3,3,3,3,3,3,3,3,3,3,3,3,3,3,3,3,3,3,3,3,3,3,3,3,3,3,3,3,3,3,3,3,3,3,3,3,3,3,3,3,3,3,3,3,3,1,
1,1,1,3,3,3,3,3,3,3,3,3,3,3,3,3,3,3,3,3,3,3,3,3,3,3,3,3,3,3,3,3,3,3,3,3,3,3,3,3,3,3,3,3,3,3,3,3,3,1,
1,1,3,3,3,3,3,3,3,3,3,3,3,3,3,3,3,3,3,3,3,3,3,3,3,3,3,3,3,3,3,3,3,3,3,3,3,3,3,3,3,3,3,3,3,3,3,3,3,1,
1,1,1,3,3,3,3,3,3,3,3,3,3,3,3,3,3,3,3,3,3,3,3,3,3,3,3,3,3,3,3,3,3,3,3,3,3,3,3,3,3,3,3,3,3,3,3,3,3,1,
1,1,1,3,3,3,3,3,3,3,3,3,3,3,3,3,3,3,3,3,3,3,3,3,3,3,3,3,3,3,3,3,3,3,3,3,3,3,3,3,3,3,3,3,3,3,3,3,3,1,
1,1,3,3,3,3,3,3,3,3,3,3,3,3,3,3,3,3,3,3,3,3,3,3,3,3,3,3,3,3,3,3,3,3,3,3,3,3,3,3,3,3,3,3,3,3,3,3,3,1,
1,1,1,3,3,3,3,3,3,3,3,3,3,3,3,3,3,3,3,3,3,3,3,3,3,3,3,3,3,3,3,3,3,3,3,3,3,3,3,3,3,3,3,3,3,3,3,3,3,1,
1,1,3,3,3,3,3,3,3,3,3,3,3,3,3,3,3,3,3,3,3,3,3,3,3,3,3,3,3,3,3,3,3,3,3,3,3,3,3,3,3,3,3,3,3,3,3,3,3,1,
1,1,3,3,3,3,3,3,3,3,3,3,3,3,3,3,3,3,3,3,3,3,3,3,3,3,3,3,3,3,3,3,3,3,3,3,3,3,3,3,3,3,3,3,3,3,3,3,3,1,
1,1,1,3,3,3,3,3,3,3,3,3,3,3,3,3,3,3,3,3,3,3,3,3,3,3,3,3,3,3,3,3,3,3,3,3,3,3,3,3,3,3,3,3,3,3,3,3,3,1,
1,1,3,3,3,3,3,3,3,3,3,3,3,3,3,3,3,3,3,3,3,3,3,3,3,3,3,3,3,3,3,3,3,3,3,3,3,3,3,3,3,3,3,3,3,3,3,3,3,1,
1,1,3,3,3,3,3,3,3,3,3,3,3,3,3,3,3,3,3,3,3,3,3,3,3,3,3,3,3,3,3,3,3,3,3,3,3,3,3,3,3,3,3,3,3,3,3,3,1,1,
1,1,3,3,3,3,3,3,3,3,3,3,3,3,3,3,3,3,3,3,3,3,3,3,3,3,3,3,3,3,3,3,3,3,3,3,3,3,3,3,3,3,3,3,3,3,3,3,3,1,
1,1,1,3,3,3,3,3,3,3,3,3,3,3,3,3,3,3,3,3,3,3,3,3,3,3,3,3,3,3,3,3,3,3,3,3,3,3,3,3,3,3,3,3,3,3,3,3,3,1,
1,1,1,3,3,3,1,1,3,1,1,3,3,1,1,1,1,1,3,3,3,1,1,1,3,3,1,1,3,1,3,3,1,3,3,1,3,3,3,1,1,3,1,1,1,1,3,3,3,1,
1,1,1,1,1,1,1,1,1,1,1,1,1,1,1,1,1,1,1,1,1,1,1,1,1,1,1,1,1,1,1,1,1,1,1,1,1,1,1,1,1,1,1,1,1,1,1,1,1,1
"		</data>
	</layer>
	<layer name="objects" width="50" height="100">
		<data encoding="csv">"
0,0,0,0,0,0,0,0,0,0,0,0,0,0,0,0,0,0,0,0,0,0,0,0,0,0,0,0,0,0,0,0,0,0,0,0,0,0,0,0,0,0,0,0,0,0,0,0,0,0,
0,0,0,0,0,0,0,0,0,0,0,0,0,0,0,0,0,0,0,0,0,0,0,0,0,0,0,0,0,0,0,0,0,0,0,0,0,0,0,0,0,0,0,0,0,0,0,0,0,0,
0,0,0,0,0,0,0,0,0,0,0,0,0,0,0,0,0,0,0,0,0,0,0,0,0,0,0,0,0,0,0,0,0,0,0,0,0,0,0,0,0,0,0,0,0,0,0,0,0,0,
0,0,0,0,0,0,0,0,0,0,0,0,0,0,0,0,0,0,0,0,0,0,0,0,0,0,0,0,0,0,0,0,0,0,0,0,0,0,0,0,0,0,0,0,0,0,0,0,0,0,
0,0,0,0,0,0,0,0,0,0,0,0,0,0,0,0,0,0,0,0,0,0,0,0,0,0,0,0,12,0,0,0,0,0,0,0,0,0,0,0,0,0,0,0,0,0,0,0,0,0,
0,0,0,0,0,0,0,0,0,0,0,0,0,0,0,0,0,0,0,0,0,0,0,0,0,0,0,0,0,68,0,0,0,0,0,0,0,0,0,0,0,0,0,0,0,0,0,0,0,0,
0,0,0,0,0,0,0,0,0,0,0,0,0,49,0,0,0,0,0,0,0,0,0,0,0,0,0,0,0,68,0,0,0,0,0,0,0,0,0,0,0,0,0,0,0,0,0,0,0,0,
0,0,0,0,0,0,0,0,0,0,0,0,0,0,0,0,0,0,0,0,0,0,0,0,0,0,0,0,0,68,0,0,0,0,0,0,0,0,0,0,0,0,0,0,0,0,0,0,0,0,
0,0,0,0,0,0,0,0,0,0,0,0,0,0,0,0,0,0,0,64,0,58,0,0,0,0,0,0,3,68,0,0,0,0,0,0,0,0,0,0,0,0,49,49,0,0,0,0,0,0,
0,0,0,0,0,49,49,0,0,0,49,0,0,0,0,0,0,0,0,0,68,0,0,0,0,0,0,0,0,68,0,0,0,19,0,0,0,0,0,0,0,0,0,0,0,0,0,0,0,0,
0,0,0,0,0,0,0,0,0,0,0,0,0,0,0,0,0,49,0,0,68,0,64,0,0,0,0,0,0,68,0,0,19,18,14,0,0,0,0,0,0,0,0,0,0,0,0,0,0,0,
0,0,0,0,0,0,49,0,0,0,0,0,0,0,0,0,0,0,0,0,0,0,0,0,0,0,0,0,73,68,73,0,0,0,0,0,0,0,0,0,0,0,0,0,0,0,0,0,0,0,
0,0,0,0,0,0,49,0,0,0,0,0,0,0,0,0,0,0,0,0,0,0,0,0,0,0,72,64,72,68,72,64,72,0,0,49,0,0,0,0,0,0,0,0,0,0,0,0,0,0,
0,0,0,0,0,0,0,0,0,0,0,0,0,0,0,0,0,0,0,49,0,0,0,0,0,0,0,0,0,0,0,0,0,0,49,49,0,0,0,64,58,0,49,0,0,0,0,0,0,0,
0,0,0,0,0,0,0,0,0,0,0,49,0,0,0,0,0,0,0,49,0,0,49,49,0,49,49,49,0,0,0,0,0,0,0,0,0,0,68,0,0,0,0,0,0,0,0,0,0,0,
0,0,0,0,0,0,0,0,0,0,49,49,0,0,0,0,0,0,0,0,0,0,49,0,0,0,0,0,0,0,0,0,0,0,0,0,0,64,68,0,0,0,0,0,49,49,0,0,0,0,
0,0,0,0,0,0,0,0,0,0,0,0,0,0,0,0,0,0,0,0,0,0,0,0,0,0,49,49,0,0,0,0,0,0,0,0,0,0,0,68,0,119,0,0,0,49,0,0,0,0,
0,0,0,0,0,0,0,0,0,0,0,0,0,0,0,0,66,66,0,0,0,0,0,0,0,0,0,49,0,0,0,0,0,0,0,0,0,0,0,0,0,0,0,0,0,0,0,0,0,0,
0,0,0,0,0,0,0,0,0,0,49,0,0,0,64,0,0,0,66,0,0,0,0,0,0,0,0,0,0,49,0,0,0,0,0,0,0,0,0,0,0,0,0,0,0,0,0,0,0,0,
0,0,0,0,0,0,0,0,0,0,0,0,0,0,64,0,0,76,0,64,0,0,0,0,0,0,0,0,0,0,0,0,0,0,0,0,0,0,0,49,49,49,49,0,0,0,0,0,0,0,
0,0,0,0,0,0,0,0,0,0,0,0,0,0,0,0,68,0,0,0,0,0,0,0,0,0,0,0,0,0,0,0,0,0,0,49,0,0,0,0,0,0,0,0,0,0,0,0,0,0,
0,0,0,0,0,0,0,0,0,0,49,0,0,0,0,0,68,0,0,0,0,0,0,0,0,0,0,0,0,0,0,0,0,0,49,49,0,0,0,0,0,0,0,0,0,0,0,0,0,0,
0,0,0,0,0,49,0,0,0,0,49,0,0,119,64,0,68,0,0,49,0,0,0,0,0,0,0,0,0,0,0,0,0,0,49,0,0,0,0,0,0,0,0,0,49,0,0,0,0,0,
0,0,0,0,0,0,0,0,0,0,49,0,0,0,0,0,68,0,49,0,0,0,0,0,0,0,0,0,0,0,0,49,0,0,0,0,0,0,0,0,0,0,0,0,0,0,0,0,0,0,
0,0,0,0,0,0,0,0,0,0,0,0,0,0,0,0,0,0,0,0,0,0,0,0,0,0,0,0,0,0,0,0,0,0,0,0,0,0,47,47,0,0,0,0,0,0,0,0,0,0,
0,0,0,0,0,0,0,0,0,0,0,0,0,49,49,0,0,0,0,0,0,0,0,0,0,0,0,0,0,0,0,0,0,0,0,0,0,0,0,0,47,47,0,0,0,0,0,0,0,0,
0,0,0,0,0,0,0,0,0,0,0,0,0,0,0,0,0,0,0,0,0,0,0,0,66,0,66,66,0,0,0,0,0,0,0,0,0,0,0,0,0,47,0,0,0,0,0,0,0,0,
0,0,0,0,0,0,0,0,0,0,0,0,0,0,0,0,0,0,0,0,0,0,0,0,0,64,58,76,64,119,0,0,0,0,0,0,0,0,0,0,0,0,0,0,0,0,0,0,0,0,
0,0,0,0,0,70,64,0,58,0,0,0,0,0,0,0,0,47,0,0,0,0,0,0,0,0,0,68,0,0,0,0,0,0,0,0,0,0,0,0,0,0,0,0,0,0,47,0,0,0,
0,0,0,0,0,0,0,0,0,68,0,0,0,0,0,0,47,47,0,0,0,0,0,0,0,0,0,0,0,0,0,0,0,0,0,0,68,0,0,0,0,0,0,0,0,0,0,0,0,0,
0,0,0,0,0,0,0,0,0,0,0,0,0,0,0,0,0,0,0,0,0,0,0,0,0,0,0,0,0,0,0,0,0,0,0,64,68,64,58,0,0,0,0,0,0,0,0,0,0,0,
0,0,0,0,0,0,0,0,0,0,0,0,0,0,0,0,0,0,0,0,0,0,0,0,0,47,0,0,0,0,0,0,0,0,0,0,68,0,0,0,0,0,0,0,0,0,0,0,0,0,
0,0,0,0,0,0,0,0,0,47,0,0,0,0,0,0,0,0,0,0,0,0,0,0,0,0,47,0,0,0,0,47,0,0,0,64,68,0,0,0,0,0,47,47,0,0,0,0,0,0,
0,0,0,0,0,0,0,0,0,0,49,0,0,0,0,0,0,0,0,0,0,0,49,49,0,0,0,0,0,0,0,47,0,0,119,0,0,0,0,0,0,0,0,0,0,0,0,0,0,0,
0,0,0,0,0,47,0,0,0,0,0,0,0,0,0,0,0,0,0,0,0,0,0,0,0,0,0,0,0,0,0,0,0,0,0,0,0,0,0,0,0,0,0,49,49,0,0,0,0,0,
0,0,0,0,0,0,0,0,0,0,0,0,0,0,0,0,0,0,0,0,0,0,0,0,0,0,0,49,49,0,0,0,0,0,0,0,0,0,0,0,0,47,0,0,0,0,0,0,0,0,
0,0,0,0,0,0,0,0,0,0,0,0,0,0,0,0,0,0,0,0,0,0,0,0,0,0,0,0,0,0,0,0,0,0,0,0,0,0,0,0,0,0,0,0,0,0,0,0,0,0,
0,0,0,0,47,0,0,0,0,0,0,0,0,49,49,0,0,0,0,68,0,0,0,0,0,0,0,0,0,0,0,0,0,0,0,47,0,0,0,0,0,0,0,0,0,0,0,0,0,0,
0,0,0,0,0,47,0,0,0,0,0,0,0,0,0,0,0,0,0,0,0,0,47,0,0,0,0,0,0,47,0,0,0,0,0,0,0,0,0,0,0,0,0,0,0,0,0,0,0,0,
0,0,0,0,0,0,0,0,0,47,0,0,0,0,0,0,0,0,0,0,0,47,47,0,0,0,47,0,0,0,0,0,0,0,0,0,0,0,0,70,64,0,0,0,0,0,0,0,0,0,
0,0,0,0,0,0,0,0,0,0,0,0,0,0,0,0,0,0,66,66,0,0,0,0,0,0,47,47,0,0,0,0,0,49,49,0,0,0,0,0,0,68,0,64,0,0,64,0,0,0,
0,0,0,0,0,0,0,0,0,0,0,0,0,0,0,0,66,64,66,0,0,0,0,0,0,0,0,0,0,0,0,0,0,0,0,0,0,0,0,0,0,0,68,0,0,0,0,0,0,0,
0,0,0,0,0,0,0,0,0,0,0,0,0,0,0,0,0,64,76,0,119,0,0,0,0,0,0,0,0,0,0,0,0,0,0,0,0,0,0,0,0,0,68,0,0,0,0,0,0,0,
0,0,0,0,0,0,0,0,47,0,50,0,0,0,0,0,68,0,0,0,0,0,0,0,0,0,0,0,0,0,0,0,0,0,0,0,47,0,0,0,119,0,68,0,0,0,0,0,0,0,
0,0,0,0,0,0,0,0,47,0,0,50,58,0,64,0,68,0,0,0,47,47,0,0,0,0,0,0,47,47,0,0,0,49,49,0,0,0,0,0,0,0,0,0,0,0,0,0,0,0,
0,0,0,0,0,0,0,0,0,0,0,0,0,0,0,0,0,0,0,0,0,0,0,0,0,0,0,0,0,0,0,0,0,0,0,0,0,0,0,0,0,0,0,0,0,0,0,0,0,0,
0,0,0,0,0,0,0,0,0,0,0,0,0,0,0,0,0,47,47,0,0,0,0,0,0,0,0,0,0,0,0,0,0,0,0,0,0,0,47,47,0,0,0,0,0,0,47,0,0,0,
0,0,0,0,0,0,47,47,0,0,0,0,0,0,0,49,0,0,0,0,0,0,0,0,0,0,83,0,0,0,0,0,0,0,0,0,0,0,0,47,47,0,0,49,0,0,0,0,0,0,
0,0,0,0,0,0,0,0,0,0,0,0,0,0,0,49,0,0,0,0,0,0,0,0,0,0,84,107,83,82,0,0,0,0,0,0,0,0,0,0,47,0,0,0,0,0,0,47,0,0,
0,0,0,0,0,0,0,0,0,0,0,0,0,0,0,0,0,0,0,0,0,0,0,0,0,0,0,0,72,0,72,0,0,0,0,0,0,0,0,0,0,0,0,0,0,0,0,0,0,0,
0,0,0,0,0,0,0,0,0,0,0,0,0,0,0,0,0,0,0,0,0,0,0,0,0,0,0,0,0,0,0,0,0,0,0,0,0,0,0,0,0,0,0,0,0,0,0,0,0,0,
0,0,0,0,0,0,0,0,0,0,0,0,0,0,0,0,0,0,0,0,0,0,0,0,0,0,0,0,0,0,0,0,0,0,0,0,0,0,0,0,0,0,0,0,0,0,0,0,0,0,
0,0,0,0,0,0,0,0,0,0,0,0,0,0,0,0,0,0,0,0,0,0,0,0,0,0,0,0,0,0,0,0,0,0,0,0,0,0,0,0,0,0,0,0,0,0,0,0,0,0,
0,0,0,0,0,0,0,0,0,0,0,0,0,0,0,0,0,0,0,0,0,0,0,0,0,0,0,0,0,0,0,0,0,0,0,0,0,0,0,0,0,0,0,0,0,0,0,0,0,0,
0,0,0,0,0,0,0,0,0,0,0,0,0,0,0,0,0,0,0,0,0,0,0,0,0,0,0,0,0,0,0,0,0,0,0,0,0,0,0,0,0,0,0,0,0,0,0,0,0,0,
0,0,0,0,0,0,0,0,0,0,0,0,0,0,0,0,0,0,0,0,0,0,0,0,0,0,0,0,0,0,0,0,0,0,0,0,0,0,0,0,0,0,0,0,0,0,0,0,0,0,
0,0,0,0,0,0,0,0,0,0,0,0,0,0,0,0,0,0,0,0,0,0,0,0,0,0,0,0,0,0,0,0,0,0,0,0,0,0,0,0,0,0,0,0,0,0,0,0,0,0,
0,0,0,0,0,0,0,0,0,0,0,0,0,0,0,0,0,0,0,0,0,0,0,0,0,0,0,0,0,0,0,0,0,0,0,0,0,0,0,0,0,0,0,0,0,0,0,0,0,0,
0,0,0,0,0,0,0,0,0,0,0,0,0,0,0,0,0,0,0,0,0,0,0,0,0,0,0,0,0,0,0,0,0,0,0,0,0,0,0,0,0,0,0,0,0,0,0,0,0,0,
0,0,0,0,0,0,0,0,0,0,0,0,0,0,0,0,0,0,0,0,0,0,0,0,0,0,0,0,0,0,0,0,0,0,0,0,0,0,0,0,0,0,0,0,0,0,0,0,0,0,
0,0,0,0,0,0,0,0,0,0,0,0,0,0,0,0,0,0,0,0,0,0,0,0,0,0,0,0,0,0,0,0,0,0,0,0,0,0,0,0,0,0,0,0,0,0,0,0,0,0,
0,0,0,0,0,0,0,0,0,0,0,0,0,0,0,0,0,0,0,0,0,0,0,0,0,0,0,0,0,0,0,0,0,0,0,0,0,0,0,0,0,0,0,0,0,0,0,0,0,0,
0,0,0,0,0,0,0,0,0,0,0,0,0,0,0,0,0,0,0,0,0,0,0,0,0,0,0,0,0,0,0,0,0,0,0,0,0,0,0,0,0,0,0,0,0,0,0,0,0,0,
0,0,0,0,0,0,0,0,0,0,0,0,0,0,0,0,0,0,0,0,0,0,0,0,0,0,0,0,0,0,0,0,0,0,0,0,0,0,0,0,0,0,0,0,0,0,0,0,0,0,
0,0,0,0,0,0,0,0,0,0,0,0,0,0,0,0,0,0,0,0,0,0,0,0,0,0,0,0,0,0,0,0,0,0,0,0,0,0,0,0,0,0,0,0,0,0,0,0,0,0,
0,0,0,0,0,0,0,0,0,0,0,0,0,0,0,0,0,0,0,0,0,0,0,0,0,0,0,0,0,0,0,0,0,0,0,0,0,0,0,0,0,0,0,0,0,0,0,0,0,0,
0,0,0,0,0,0,0,0,0,0,0,0,0,0,0,0,0,0,0,0,0,0,0,0,0,0,0,0,0,0,0,0,0,0,0,0,0,0,0,0,0,0,0,0,0,0,0,0,0,0,
0,0,0,0,0,0,0,0,0,0,0,0,0,0,0,0,0,0,0,0,0,0,0,0,0,0,0,0,0,0,0,0,0,0,0,0,0,0,0,0,0,0,0,0,0,0,0,0,0,0,
0,0,0,0,0,0,0,0,0,0,0,0,0,0,0,0,0,0,0,0,0,0,0,0,0,0,0,0,0,0,0,0,0,0,0,0,0,0,0,0,0,0,0,0,0,0,0,0,0,0,
0,0,0,0,0,0,0,0,0,0,0,0,0,0,0,0,0,0,0,0,0,0,0,0,0,0,0,0,0,0,0,0,0,0,0,0,0,0,0,0,0,0,0,0,0,0,0,0,0,0,
0,0,0,0,0,0,0,0,0,0,0,0,0,0,0,0,0,0,0,0,0,0,0,0,0,0,0,0,0,0,0,0,0,0,0,0,0,0,0,0,0,0,0,0,0,0,0,0,0,0,
0,0,0,0,0,0,0,0,0,0,0,0,0,0,0,0,0,0,0,0,0,0,0,0,0,0,0,0,0,0,0,0,0,0,0,0,0,0,0,0,0,0,0,0,0,0,0,0,0,0,
0,0,0,0,0,0,0,0,0,0,0,0,0,0,0,0,0,0,0,0,0,0,0,0,0,0,0,0,0,0,0,0,0,0,0,0,0,0,0,0,0,0,0,0,0,0,0,0,0,0,
0,0,0,0,0,0,0,0,0,0,0,0,0,0,0,0,0,0,0,0,0,0,0,0,0,0,0,0,0,0,0,0,0,0,0,0,0,0,0,0,0,0,0,0,0,0,0,0,0,0,
0,0,0,0,0,0,0,0,0,0,0,0,0,0,0,0,0,0,0,0,0,0,0,0,0,0,0,0,0,0,0,0,0,0,0,0,0,0,0,0,0,0,0,0,0,0,0,0,0,0,
0,0,0,0,0,0,0,0,0,0,0,0,0,0,0,0,0,0,0,0,0,0,0,0,0,0,0,0,0,0,0,0,0,0,0,0,0,0,0,0,0,0,0,0,0,0,0,0,0,0,
0,0,0,0,0,0,0,0,0,0,0,0,0,0,0,0,0,0,0,0,0,0,0,0,0,0,0,0,0,0,0,0,0,0,0,0,0,0,0,0,0,0,0,0,0,0,0,0,0,0,
0,0,0,0,0,0,0,0,0,0,0,0,0,0,0,0,0,0,0,0,0,0,0,0,0,0,0,0,0,0,0,0,0,0,0,0,0,0,0,0,0,0,0,0,0,0,0,0,0,0,
0,0,0,0,0,0,0,0,0,0,0,0,0,0,0,0,0,0,0,0,0,0,0,0,0,0,0,0,0,0,0,0,0,0,0,0,0,0,0,0,0,0,0,0,0,0,0,0,0,0,
0,0,0,0,0,0,0,0,0,0,0,0,0,0,0,0,0,0,0,0,0,0,0,0,0,0,0,0,0,0,0,0,0,0,0,0,0,0,0,0,0,0,0,0,0,0,0,0,0,0,
0,0,0,0,0,0,0,0,0,0,0,0,0,0,0,0,0,0,0,0,0,0,0,0,0,0,0,0,0,0,0,0,0,0,0,0,0,0,0,0,0,0,0,0,0,0,0,0,0,0,
0,0,0,0,0,0,0,0,0,0,0,0,0,0,0,0,0,0,0,0,0,0,0,0,0,0,0,0,0,0,0,0,0,0,0,0,0,0,0,0,0,0,0,0,0,0,0,0,0,0,
0,0,0,0,0,0,0,0,0,0,0,0,0,0,0,0,0,0,0,0,0,0,0,0,0,0,0,0,0,0,0,0,0,0,0,0,0,0,0,0,0,0,0,0,0,0,0,0,0,0,
0,0,0,0,0,0,0,0,0,0,0,0,0,0,0,0,0,0,0,0,0,0,0,0,0,0,0,0,0,0,0,0,0,0,0,0,0,0,0,0,0,0,0,0,0,0,0,0,0,0,
0,0,0,0,0,0,0,0,0,0,0,0,0,0,0,0,0,0,0,0,0,0,0,0,0,0,0,0,0,0,0,0,0,0,0,0,0,0,0,0,0,0,0,0,0,0,0,0,0,0,
0,0,0,0,0,0,0,0,0,0,0,0,0,0,0,0,0,0,0,0,0,0,0,0,0,0,0,0,0,0,0,0,0,0,0,0,0,0,0,0,0,0,0,0,0,0,0,0,0,0,
0,0,0,0,0,0,0,0,0,0,0,0,0,0,0,0,0,0,0,0,0,0,0,0,0,0,0,0,0,0,0,0,0,0,0,0,0,0,0,0,0,0,0,0,0,0,0,0,0,0,
0,0,0,0,0,0,0,0,0,0,0,0,0,0,0,0,0,0,0,0,0,0,0,0,0,0,0,0,0,0,0,0,0,0,0,0,0,0,0,0,0,0,0,0,0,0,0,0,0,0,
0,0,0,0,0,0,0,0,0,0,0,0,0,0,0,0,0,0,0,0,0,0,0,0,0,0,0,0,0,0,0,0,0,0,0,0,0,0,0,0,0,0,0,0,0,0,0,0,0,0,
0,0,0,0,0,0,0,0,0,0,0,0,0,0,0,0,0,0,0,0,0,0,0,0,0,0,0,0,0,0,0,0,0,0,0,0,0,0,0,0,0,0,0,0,0,0,0,0,0,0,
0,0,0,0,0,0,0,0,0,0,0,0,0,0,0,0,0,0,0,0,0,0,0,0,0,0,0,0,0,0,0,0,0,0,0,0,0,0,0,0,0,0,0,0,0,0,0,0,0,0,
0,0,0,0,0,0,0,0,0,0,0,0,0,0,0,0,0,0,0,0,0,0,0,0,0,0,0,0,0,0,0,0,0,0,0,0,0,0,0,0,0,0,0,0,0,0,0,0,0,0,
0,0,0,0,0,0,0,0,0,0,0,0,0,0,0,0,0,0,0,0,0,0,0,0,0,0,0,0,0,0,0,0,0,0,0,0,0,0,0,0,0,0,0,0,0,0,0,0,0,0,
0,0,0,0,0,0,0,0,0,0,0,0,0,0,0,0,0,0,0,0,0,0,0,0,0,0,0,0,0,0,0,0,0,0,0,0,0,0,0,0,0,0,0,0,0,0,0,0,0,0,
0,0,0,0,0,0,0,0,0,0,0,0,0,0,0,0,0,0,0,0,0,0,0,0,0,0,0,0,0,0,0,0,0,0,0,0,0,0,0,0,0,0,0,0,0,0,0,0,0,0,
0,0,0,0,0,0,0,0,0,0,0,0,0,0,0,0,0,0,0,0,0,0,0,0,0,0,0,0,0,0,0,0,0,0,0,0,0,0,0,0,0,0,0,0,0,0,0,0,0,0,
0,0,0,0,0,0,0,0,0,0,0,0,0,0,0,0,0,0,0,0,0,0,0,0,0,0,0,0,0,0,0,0,0,0,0,0,0,0,0,0,0,0,0,0,0,0,0,0,0,0,
0,0,0,0,0,0,0,0,0,0,0,0,0,0,0,0,0,0,0,0,0,0,0,0,0,0,0,0,0,0,0,0,0,0,0,0,0,0,0,0,0,0,0,0,0,0,0,0,0,0,
0,0,0,0,0,0,0,0,0,0,0,0,0,0,0,0,0,0,0,0,0,0,0,0,0,0,0,0,0,0,0,0,0,0,0,0,0,0,0,0,0,0,0,0,0,0,0,0,0,0,
0,0,0,0,0,0,0,0,0,0,0,0,0,0,0,0,0,0,0,0,0,0,0,0,0,0,0,0,0,0,0,0,0,0,0,0,0,0,0,0,0,0,0,0,0,0,0,0,0,0
"		</data>
	</layer>
	<objectgroup name="meta" width="50" height="100" visible="0">
		<object x="640" y="3712">
			<polyline points="0,0 4352,1408" />
		</object>
	</objectgroup>
</map>
